mnrva/__init__.py
mnrva/engines.py
mnrva/fs.py
mnrva/scraping.py
mnrva/utils.py
mnrva-0.0.8.dist-info/LICENSE
mnrva-0.0.8.dist-info/METADATA
mnrva-0.0.8.dist-info/WHEEL
mnrva-0.0.8.dist-info/top_level.txt
mnrva-0.0.8.dist-info/RECORD
